csp_adapter_slack/__init__.py
csp_adapter_slack/adapter.py
csp_adapter_slack/adapter_config.py
csp_adapter_slack/mention.py
csp_adapter_slack/message.py
csp_adapter_slack/examples/__init__.py
csp_adapter_slack/examples/hello.py
csp_adapter_slack/tests/test_adapter.py
csp_adapter_slack-0.3.0.dist-info/METADATA
csp_adapter_slack-0.3.0.dist-info/WHEEL
csp_adapter_slack-0.3.0.dist-info/licenses/LICENSE
csp_adapter_slack-0.3.0.dist-info/RECORD
