Metadata-Version: 2.4
Name: csp_adapter_slack
Version: 0.3.0
Summary: A csp adapter for slack
Project-URL: Repository, https://github.com/point72/csp-adapter-slack
Project-URL: Homepage, https://github.com/point72/csp-adapter-slack
Author-email: the csp authors <CSPOpenSource@point72.com>
License:                                  Apache License
License-File: LICENSE
Keywords: chat,chatbot,csp,slack,stream-processing
Classifier: Development Status :: 4 - Beta
Classifier: Framework :: Jupyter
Classifier: License :: OSI Approved :: Apache Software License
Classifier: Programming Language :: Python
Classifier: Programming Language :: Python :: 3
Classifier: Programming Language :: Python :: 3.9
Classifier: Programming Language :: Python :: 3.10
Classifier: Programming Language :: Python :: 3.11
Classifier: Programming Language :: Python :: 3.12
Classifier: Programming Language :: Python :: 3.13
Requires-Python: >=3.9
Requires-Dist: csp
Requires-Dist: pydantic>=2
Requires-Dist: slack-sdk>=3
Provides-Extra: develop
Requires-Dist: bump-my-version; extra == 'develop'
Requires-Dist: check-manifest; extra == 'develop'
Requires-Dist: codespell<2.5,>=2.2.6; extra == 'develop'
Requires-Dist: hatchling; extra == 'develop'
Requires-Dist: mdformat-tables<1.1,>=1; extra == 'develop'
Requires-Dist: mdformat<0.8,>=0.7.17; extra == 'develop'
Requires-Dist: pytest; extra == 'develop'
Requires-Dist: pytest-cov; extra == 'develop'
Requires-Dist: ruff<0.12,>=0.5; extra == 'develop'
Requires-Dist: twine<7,>=5; extra == 'develop'
Provides-Extra: test
Requires-Dist: pytest; extra == 'test'
Requires-Dist: pytest-cov; extra == 'test'
